CodeToClassDiagram/__init__.py
CodeToClassDiagram/config.py
CodeToClassDiagram/main.py
CodeToClassDiagram/configs/__init__.py
CodeToClassDiagram/configs/config.json
CodeToClassDiagram/configs/internal_config.json
CodeToClassDiagram/data/__init__.py
CodeToClassDiagram/data/conversion.py
CodeToClassDiagram/data/method.py
CodeToClassDiagram/data/namespace.py
CodeToClassDiagram/data/parameter.py
CodeToClassDiagram/data/parsed_member.py
CodeToClassDiagram/data/parsed_type.py
CodeToClassDiagram/data/project.py
CodeToClassDiagram/data/property.py
CodeToClassDiagram/diagram/__init__.py
CodeToClassDiagram/diagram/display_utils.py
CodeToClassDiagram/diagram/mermaid_display.py
CodeToClassDiagram/diagram/plantuml_display.py
CodeToClassDiagram/parsing/__init__.py
CodeToClassDiagram/parsing/csharp/__init__.py
CodeToClassDiagram/parsing/csharp/queries.py
CodeToClassDiagram/parsing/csharp/ts_parser.py
codetoclassdiagram-1.1.7.dist-info/METADATA
codetoclassdiagram-1.1.7.dist-info/WHEEL
codetoclassdiagram-1.1.7.dist-info/entry_points.txt
codetoclassdiagram-1.1.7.dist-info/top_level.txt
codetoclassdiagram-1.1.7.dist-info/RECORD
